server.py
monarch_money_mcp_enhanced-0.11.6.dist-info/METADATA
monarch_money_mcp_enhanced-0.11.6.dist-info/WHEEL
monarch_money_mcp_enhanced-0.11.6.dist-info/entry_points.txt
monarch_money_mcp_enhanced-0.11.6.dist-info/top_level.txt
monarch_money_mcp_enhanced-0.11.6.dist-info/RECORD
