Metadata-Version: 2.4
Name: monarch-money-mcp-enhanced
Version: 0.11.6
Summary: Enhanced MCP server for MonarchMoney financial data access with dynamic tool generation
Requires-Python: >=3.11
Requires-Dist: mcp>=1.9.4
Requires-Dist: monarchmoney-enhanced>=0.11.0
Provides-Extra: test
Requires-Dist: pytest>=8.0.0; extra == "test"
Requires-Dist: pytest-asyncio>=0.21.0; extra == "test"
Requires-Dist: pytest-mock>=3.10.0; extra == "test"
Requires-Dist: toml>=0.10.2; extra == "test"
